Sources/spi.v
/*
 * Simple SPI interface
 * Suoglu, Des 2020
 */

module spi_master#(parameter SLAVE_COUNT = 8, parameter SLAVE_ADDRS_LEN = 3)(
  input clk,
  input rst, 
  input start_trans, //Start transaction
  output busy, 
  output reg MOSI, 
  input MISO, 
  output SPI_SCLK, 
  output reg [(SLAVE_COUNT-1):0] CS, 
  input [31:0] tx_data, 
  output reg [31:0] rx_data, 
  input [(SLAVE_ADDRS_LEN-1):0] chipADDRS, 
  input [1:0] transaction_length, //0x00 8bit, 0x01 16bit, 0x10 24bit, 0x11 32bit
  input clkDiv_en, //Enable clock divider
  input [3:0] division_ratio,
  input CPOL, //Clock polarity
  input default_val);
  //SPI state related signals
  parameter SPI_READY   = 2'b00, //Ready for new process
            SPI_PRE_Tx  = 2'b01, //Pre transfer process
            SPI_Tx  = 2'b11, //SPI transfer in progress
            SPI_POST_Tx = 2'b10; //Post transfer process
  reg [4:0] SPI_transaction_counter;
  reg [1:0] SPI_state;
  wire SPI_ready, SPI_pre_t, SPI_working, SPI_post_t;
  //Buffers
  reg [31:0] rx_buff;
  reg [32:0] tx_buff;
  //Counters and clocking
  wire [15:0] clk_array;
  wire spi_clk_main; //Main SPI clock 
  wire spi_clk_sys; //SPI clock to be used in the module
  reg stopper;
  
  clockDiv16 clock_div((clk & clkDiv_en), rst, clk_array);

  //Decode states
  assign SPI_ready = (SPI_state == SPI_READY);
  assign SPI_pre_t = (SPI_state == SPI_PRE_Tx);
  assign SPI_working = (SPI_state == SPI_Tx);
  assign SPI_post_t = (SPI_state == SPI_POST_Tx);
  assign busy = ~SPI_ready;

  //Generated clock or external clock
  assign spi_clk_main = (clkDiv_en) ? clk_array[division_ratio] : clk;
  //SPI clock should not work when not in use
  assign SPI_SCLK = (SPI_working) ? (CPOL ^ spi_clk_main) : CPOL;
  //Clock polarisation and phase adjustment for inner logic
  assign spi_clk_sys = (SPI_SCLK ^ CPOL);

  //SPI states
  always@(posedge clk)
    begin
      if(rst)
        begin
          SPI_state <= SPI_READY;
        end
      else
        begin
          case(SPI_state)
            SPI_READY:
              begin
                SPI_state <= (start_trans) ? SPI_PRE_Tx : SPI_READY;
              end
            SPI_PRE_Tx:
              begin
                SPI_state <= (CPOL == SPI_SCLK) ? SPI_Tx : SPI_PRE_Tx;
              end
            SPI_Tx:
              begin
                SPI_state <= (((~|SPI_transaction_counter) & (CPOL == SPI_SCLK)) & (~stopper)) ? SPI_POST_Tx : SPI_Tx;
              end
            SPI_POST_Tx:
              begin
                SPI_state <= SPI_READY;
              end
          endcase
        end
    end

  //SPI transaction counter
  always@(posedge spi_clk_sys or posedge SPI_pre_t)
    begin
      if(SPI_pre_t)
        begin
          case(transaction_length)
            2'b00: //8bit
              begin
                SPI_transaction_counter <= 5'd24;
              end
            2'b01: //16bit
              begin
                SPI_transaction_counter <= 5'd16;
              end
            2'b10: //24bit
              begin
                SPI_transaction_counter <= 5'd8;
              end
            2'b11: //32bit
              begin
                SPI_transaction_counter <= 5'd0;
              end
          endcase
        end
      else
        begin
          SPI_transaction_counter <= SPI_transaction_counter + 5'd1;
        end
    end
  
  //Stopper for early termination
  always@(posedge clk)
    begin
      case(SPI_state)
        SPI_READY:
          begin
            stopper <= 1;
          end
        SPI_Tx:
          begin
            stopper <= (SPI_transaction_counter == 5'd27) ? 0 : stopper;
          end
      endcase
    end

  //MOSI handle according to Tx leght
  always@*
    begin
      if(busy)
        case(transaction_length)
          2'd0:
            begin
              MOSI = tx_buff[7];
            end
          2'd1:
            begin
              MOSI = tx_buff[15];
            end
          2'd2:
            begin
              MOSI = tx_buff[23];
            end
          2'd3:
            begin
              MOSI = tx_buff[31];
            end 
        endcase
      else
        MOSI = default_val;
    end
  
  //Transmit buffer
  always@(negedge spi_clk_sys or posedge SPI_pre_t)
    begin
      if(SPI_pre_t)
        begin
          tx_buff <= {default_val, tx_data};
        end
      else
        begin
          tx_buff <= {tx_buff[31:0], default_val};
        end
    end
  
  //Receive buffer
  always@(posedge spi_clk_sys or posedge SPI_pre_t)
    begin
      if(SPI_pre_t)
        begin
          rx_buff <= 32'h0;
        end
      else
        begin
          rx_buff <= {rx_buff[30:0], MISO};
        end
    end
  
  //Store receive buffer data to rx_data
  always@(negedge SPI_post_t)
    begin
      rx_data <= rx_buff;
    end

  //Chip (Slave) select
  always@(posedge clk)
    begin
      if(rst)
        begin
          CS <= {SLAVE_COUNT{1'b1}};
        end
      else
        begin
          case(SPI_state)
            SPI_READY:
              begin
                CS[chipADDRS] <= ~start_trans;
              end
            SPI_POST_Tx:
              begin
                CS <= {SLAVE_COUNT{1'b1}};
              end
          endcase
        end
    end
endmodule

 /*
  + Output rates, clk_o[n], for 100MHz input clock:
  +   n         Freq
  + 0000:    50       MHz
  + 0001:    25       MHz
  + 0010:    12.5     MHz
  + 0011:     6.25    MHz
  + 0100:     3.125   MHz
  + 0101:  1562.5     kHz
  + 0110:   781.25    kHz
  + 0111:   390.625   kHz
  + 1000:   195.312   kHz
  + 1001:    97.656   kHz
  + 1010:    48.828   kHz
  + 1011:    24.414   kHz
  + 1100:    12.207   kHz
  + 1101:     6.103   kHz
  + 1110:     3.052   kHz
  + 1111:     1.526   kHz
  */
//Clock divider module
module clockDiv16(clk_i, rst, clk_o);
  input clk_i, rst;
  output [15:0] clk_o;  
  reg [15:0] clk_array; //Clock generation array, asynchronous reset

  assign clk_o = clk_array;

  //Clock dividers
  always@(posedge clk_i or posedge rst)
    begin
      if(rst)
        begin
          clk_array[0] <= 0;
        end
      else
        begin
          clk_array[0] <= ~clk_array[0];
        end
    end

    genvar i;
    generate
      for (i = 0; i < 15; i = i + 1) 
        begin
          always@(posedge clk_array[i] or posedge rst)
            begin
              if(rst)
                begin
                  clk_array[i+1] <= 0;
                end
              else
                begin
                  clk_array[i+1] <= ~clk_array[i+1];
                end
            end
        end
    endgenerate
endmodule//clockDiv16

Simulation/tb.v
`timescale 1ns / 1ps
`include "Sources/spi.v"

module testbench();
    reg clk, rst, start_trans, default_val, CPOL, CPHA, clkDiv_en;
    wire busy_m, busy_s, MOSI, SPI_SCLK, spi_clk_sys, spi_clk_sys_correct, MISO,stay;
    wire [31:0] rx_data_m, rx_data_s;
    wire [1:0] SPI_state;
    wire [4:0] SPI_transaction_counter;
    wire [7:0] CS;
    reg [31:0] tx_data_m, tx_data_s;
    reg [1:0] transaction_length;
    reg [2:0] chipADDRS;
    reg [3:0] division_ratio;
    wire [32:0] tx_buff;

    always #5 clk <= ~clk;

    assign MISO = MOSI;

    spi_master master_uut(clk, rst, start_trans, busy_m, MOSI, MISO, SPI_SCLK, CS, tx_data_m, rx_data_m, 3'd0, transaction_length, 1'b1, 4'd1, CPOL, 1'b0);

    initial //Tracked signals & Total sim time
        begin
          $dumpfile("Simulation/spi.vcd");
          $dumpvars(0, clk);
          $dumpvars(1, rst);
          $dumpvars(2, transaction_length);
          $dumpvars(3, CPOL);
          $dumpvars(4, CPHA);
          $dumpvars(5, MOSI);
          $dumpvars(6, MISO);
          $dumpvars(7, rx_data_m);
          $dumpvars(8, tx_data_s);
          $dumpvars(7, rx_data_s);
          $dumpvars(8, tx_data_m);
          $dumpvars(9, busy_m);
          $dumpvars(10, busy_s);
          $dumpvars(11, SPI_SCLK);
          $dumpvars(12, CS);
          $dumpvars(13, start_trans);
         // $dumpvars(14, start_trans);
          #2000
          $finish;
        end

    initial //initilizations and reset
        begin
            clk <= 0;
            rst <= 0;
            start_trans <= 0;
            //CPHA <= 0;
            CPOL <= 1;
            transaction_length <= 2'd0;
            #3
            rst <= 1;
            #10
            rst <= 0;
        end

    initial //Testcases
        begin
          tx_data_m <= 32'b1100_1010;
          tx_data_s <= 32'd242;
          #40
          start_trans <= 1;
          #20
          start_trans <= 0;
          #450
          tx_data_m <= 32'b1001_0110_0000_0010_1100_0101_1100_1010;
          transaction_length <= 2'd3;
          #40
          start_trans <= 1;
          #20
          start_trans <= 0;
        end
endmodule//testbench

Simulation/master_self_test.vcd
$date
	Wed Dec  2 00:39:04 2020
$end
$version
	Icarus Verilog
$end
$timescale
	1ps
$end
$scope module testbench $end
$var reg 1 ! clk $end
$upscope $end
$scope module testbench $end
$var reg 1 " rst $end
$upscope $end
$scope module testbench $end
$var reg 2 # transaction_length [1:0] $end
$upscope $end
$scope module testbench $end
$var reg 1 $ CPOL $end
$upscope $end
$scope module testbench $end
$var reg 1 % CPHA $end
$upscope $end
$scope module testbench $end
$var wire 1 & MOSI $end
$upscope $end
$scope module testbench $end
$var wire 1 ' MISO $end
$upscope $end
$scope module testbench $end
$var wire 32 ( rx_data_m [31:0] $end
$upscope $end
$scope module testbench $end
$var reg 32 ) tx_data_s [31:0] $end
$upscope $end
$scope module testbench $end
$var wire 32 * rx_data_s [31:0] $end
$upscope $end
$scope module testbench $end
$var reg 32 + tx_data_m [31:0] $end
$upscope $end
$scope module testbench $end
$var wire 1 , busy_m $end
$upscope $end
$scope module testbench $end
$var wire 1 - busy_s $end
$upscope $end
$scope module testbench $end
$var wire 1 . SPI_SCLK $end
$upscope $end
$scope module testbench $end
$var wire 8 / CS [7:0] $end
$upscope $end
$scope module testbench $end
$var reg 1 0 start_trans $end
$upscope $end
$enddefinitions $end
#0
$dumpvars
00
bx /
x.
z-
x,
b11001010 +
bz *
b11110010 )
bx (
0'
0&
x%
1$
b0 #
0"
0!
$end
#3000
1.
1"
#5000
0,
b11111111 /
1!
#10000
0!
#13000
0"
#15000
1!
#20000
0!
#25000
1!
#30000
0!
#35000
1!
#40000
0!
10
#45000
1'
1&
1,
b11111110 /
1!
#50000
0!
#55000
0.
1!
#60000
0!
00
#65000
1!
#70000
0!
#75000
1.
1!
#80000
0!
#85000
1!
#90000
0!
#95000
0.
1!
#100000
0!
#105000
1!
#110000
0!
#115000
0'
0&
1.
1!
#120000
0!
#125000
1!
#130000
0!
#135000
0.
1!
#140000
0!
#145000
1!
#150000
0!
#155000
1.
1!
#160000
0!
#165000
1!
#170000
0!
#175000
0.
1!
#180000
0!
#185000
1!
#190000
0!
#195000
1'
1&
1.
1!
#200000
0!
#205000
1!
#210000
0!
#215000
0.
1!
#220000
0!
#225000
1!
#230000
0!
#235000
0'
0&
1.
1!
#240000
0!
#245000
1!
#250000
0!
#255000
0.
1!
#260000
0!
#265000
1!
#270000
0!
#275000
1'
1&
1.
1!
#280000
0!
#285000
1!
#290000
0!
#295000
0.
1!
#300000
0!
#305000
1!
#310000
0!
#315000
0'
0&
1.
1!
#320000
0!
#325000
1!
#330000
0!
#335000
0.
1!
#340000
0!
#345000
1!
#350000
0!
#355000
1.
1!
#360000
0!
#365000
1!
#370000
0!
#375000
b11001010 (
0,
b11111111 /
1!
#380000
0!
#385000
1!
#390000
0!
#395000
1!
#400000
0!
#405000
1!
#410000
0!
#415000
1!
#420000
0!
#425000
1!
#430000
0!
#435000
1!
#440000
0!
#445000
1!
#450000
0!
#455000
1!
#460000
0!
#465000
1!
#470000
0!
#475000
1!
#480000
0!
#485000
1!
#490000
0!
#495000
1!
#500000
0!
#505000
1!
#510000
0!
b11 #
b10010110000000101100010111001010 +
#515000
1!
#520000
0!
#525000
1!
#530000
0!
#535000
1!
#540000
0!
#545000
1!
#550000
0!
10
#555000
1'
1&
1,
b11111110 /
1!
#560000
0!
#565000
1!
#570000
0!
00
#575000
0.
1!
#580000
0!
#585000
1!
#590000
0!
#595000
0'
0&
1.
1!
#600000
0!
#605000
1!
#610000
0!
#615000
0.
1!
#620000
0!
#625000
1!
#630000
0!
#635000
1.
1!
#640000
0!
#645000
1!
#650000
0!
#655000
0.
1!
#660000
0!
#665000
1!
#670000
0!
#675000
1'
1&
1.
1!
#680000
0!
#685000
1!
#690000
0!
#695000
0.
1!
#700000
0!
#705000
1!
#710000
0!
#715000
0'
0&
1.
1!
#720000
0!
#725000
1!
#730000
0!
#735000
0.
1!
#740000
0!
#745000
1!
#750000
0!
#755000
1'
1&
1.
1!
#760000
0!
#765000
1!
#770000
0!
#775000
0.
1!
#780000
0!
#785000
1!
#790000
0!
#795000
1.
1!
#800000
0!
#805000
1!
#810000
0!
#815000
0.
1!
#820000
0!
#825000
1!
#830000
0!
#835000
0'
0&
1.
1!
